vaers.py
vaers-0.0.4.dist-info/METADATA
vaers-0.0.4.dist-info/WHEEL
vaers-0.0.4.dist-info/entry_points.txt
vaers-0.0.4.dist-info/top_level.txt
vaers-0.0.4.dist-info/RECORD
