Metadata-Version: 2.1
Name: vaers
Version: 0.0.4
Summary: A package for adverse effects on death using VAERS
Home-page: https://github.com/y-takefuji/safety_vaccine
Author: yoshiyasu takefuji
Author-email: takefuji@keio.jp
License: UNKNOWN
Project-URL: Bug Tracker, https://github.com/y-takefuji/safety_vaccine
Platform: UNKNOWN
Classifier: Programming Language :: Python :: 3
Classifier: License :: OSI Approved :: MIT License
Classifier: Operating System :: OS Independent
Requires-Python: >=3.8
